cascade/__init__.py
cascade/orderer.py
cascade/py.typed
cascade_rivers-2.1.0.dist-info/AUTHORS.rst
cascade_rivers-2.1.0.dist-info/LICENSE
cascade_rivers-2.1.0.dist-info/METADATA
cascade_rivers-2.1.0.dist-info/WHEEL
cascade_rivers-2.1.0.dist-info/top_level.txt
cascade_rivers-2.1.0.dist-info/RECORD
